taskme/__init__.py
taskme-0.0.1a1.dist-info/METADATA
taskme-0.0.1a1.dist-info/WHEEL
taskme-0.0.1a1.dist-info/entry_points.txt
taskme-0.0.1a1.dist-info/licenses/LICENSE
taskme-0.0.1a1.dist-info/RECORD
