Metadata-Version: 2.4
Name: taskme
Version: 0.0.1a1
Summary: Create tasks in your project management tools when you write TODO comments
Project-URL: Repository, https://github.com/mikkothegeeko/taskme
Project-URL: Documentation, https://mikkothegeeko.github.io/taskme/
Project-URL: Changelog, https://github.com/mikkothegeeko/taskme/blob/main/CHANGELOG.md
Author-email: mikko <mbayabo@gmail.com>
License:                                  Apache License
License-File: LICENSE
Keywords: automation,comment,issue,management,project,task,todo
Classifier: Development Status :: 1 - Planning
Classifier: Environment :: Console
Classifier: Intended Audience :: Developers
Classifier: Operating System :: OS Independent
Classifier: Programming Language :: Python
Classifier: Programming Language :: Python :: 3 :: Only
Classifier: Programming Language :: Python :: 3.10
Classifier: Programming Language :: Python :: 3.11
Classifier: Programming Language :: Python :: 3.12
Classifier: Programming Language :: Python :: 3.13
Classifier: Topic :: Software Development :: Libraries :: Python Modules
Requires-Python: <3.13,>=3.10
Requires-Dist: pydantic>=2.10.4
Requires-Dist: typer>=0.15.1
